// class version 50.0 (50)
// access flags 0x21
public class Employee {

  // compiled from: Employee.java

  // access flags 0x2
  private LString; name

  // access flags 0x2
  private I age

  // access flags 0x1
  public <init>(LString;I)V
   L0
    LINENUMBER 11 L0
    ALOAD 0
    INVOKESPECIAL Object.<init> ()V
   L1
    LINENUMBER 12 L1
    ALOAD 0
    ALOAD 1
    PUTFIELD Employee.name : LString;
   L2
    LINENUMBER 13 L2
    ALOAD 0
    ILOAD 2
    PUTFIELD Employee.age : I
   L3
    LINENUMBER 14 L3
    RETURN
   L4
    LOCALVARIABLE this LEmployee; L0 L4 0
    LOCALVARIABLE name LString; L0 L4 1
    LOCALVARIABLE age I L0 L4 2
    MAXSTACK = 2
    MAXLOCALS = 3

  // access flags 0x9
  // signature ([LEmployee;)LSet<LEmployee;>;
  // declaration: Set<Employee> employeesOver40(Employee[])
  public static employeesOver40([LEmployee;)LSet;
   L0
    LINENUMBER 17 L0
   FRAME FULL [[LEmployee;] []
    NEW HashSet
    DUP
    INVOKESPECIAL HashSet.<init> ()V
    ASTORE 1
   L1
    LINENUMBER 18 L1
    ALOAD 0
    DUP
    ASTORE 5
    ARRAYLENGTH
    ISTORE 4
    ICONST_0
    ISTORE 3
    GOTO L2
   L3
   FRAME FULL [[LEmployee; Set T I I [LEmployee;] []
    ALOAD 5
    ILOAD 3
    AALOAD
    ASTORE 2
   L4
    LINENUMBER 19 L4
    ALOAD 2
    GETFIELD Employee.age : I
    BIPUSH 40
    IF_ICMPLE L5
   L6
    LINENUMBER 20 L6
    ALOAD 1
    ALOAD 2
    INVOKEINTERFACE Set.add (LObject;)Z
    POP
   L5
    LINENUMBER 18 L5
   FRAME FULL [[LEmployee; Set T I I [LEmployee;] []
    IINC 3 1
   L2
   FRAME FULL [[LEmployee; Set T I I [LEmployee;] []
    ILOAD 3
    ILOAD 4
    IF_ICMPLT L3
   L7
    LINENUMBER 23 L7
    ALOAD 1
    ARETURN
   L8
    LOCALVARIABLE input [LEmployee; L0 L8 0
    LOCALVARIABLE result LSet; L1 L8 1
    // signature LSet<LEmployee;>;
    // declaration: Set<Employee>
    LOCALVARIABLE e LEmployee; L4 L5 2
    MAXSTACK = 2
    MAXLOCALS = 6

  // access flags 0x9
  public static main([LString;)V
   L0
    LINENUMBER 28 L0
   FRAME FULL [[LString;] []
   FRAME FULL [[LString;] []
    INVOKESTATIC Employee.foo ()V
   L1
    LINENUMBER 27 L1
    GOTO L0
   L2
    LOCALVARIABLE args [LString; L0 L2 0
    MAXSTACK = 0
    MAXLOCALS = 1

  // access flags 0x9
  public static foo()V
   L0
    LINENUMBER 34 L0
    RETURN
    MAXSTACK = 0
    MAXLOCALS = 0
}
